richerr/__init__.py
richerr-0.3.0.dist-info/LICENSE
richerr-0.3.0.dist-info/METADATA
richerr-0.3.0.dist-info/WHEEL
richerr-0.3.0.dist-info/RECORD
