Metadata-Version: 2.1
Name: RichErr
Version: 0.3.0
Summary: Rich errors (sort of)
Home-page: https://adambrianbright.github.io/python-richerr/
License: MIT
Keywords: errors,exceptions,json
Author: Bogdan Parfenov
Author-email: adam.brian.bright@gmail.com
Requires-Python: >=3.12.0,<4.0
Classifier: Development Status :: 4 - Beta
Classifier: Environment :: Console
Classifier: Intended Audience :: Developers
Classifier: License :: OSI Approved :: MIT License
Classifier: Natural Language :: English
Classifier: Natural Language :: Russian
Classifier: Operating System :: MacOS :: MacOS X
Classifier: Operating System :: Microsoft :: Windows :: Windows 10
Classifier: Operating System :: OS Independent
Classifier: Operating System :: POSIX :: Linux
Classifier: Programming Language :: Python :: 3
Classifier: Programming Language :: Python :: 3 :: Only
Classifier: Programming Language :: Python :: 3.10
Classifier: Topic :: Software Development
Classifier: Topic :: Software Development :: Libraries
Classifier: Topic :: Software Development :: Libraries :: Python Modules
Classifier: Topic :: Utilities
Classifier: Typing :: Typed
Project-URL: Bug Tracker, https://github.com/AdamBrianBright/python-richerr/issues
Project-URL: ChangeLog, https://adambrianbright.github.io/python-richerr/changelog
Project-URL: Contact Author, https://vk.com/adam_bright
Project-URL: Documentation, https://adambrianbright.github.io/python-richerr/
Project-URL: Repository, https://github.com/AdamBrianBright/python-richerr
